gracklepy/__config__.py
gracklepy/__init__.py
gracklepy/fluid_container.py
gracklepy/grackle_defs.pxd
gracklepy/grackle_wrapper.cpython-312-x86_64-linux-musl.so
gracklepy/grackle_wrapper.pyx
gracklepy/libgrackle-3.4.1.so
gracklepy/yt_fields.py
gracklepy/utilities/__init__.py
gracklepy/utilities/convenience.py
gracklepy/utilities/data_path.py
gracklepy/utilities/evolve.py
gracklepy/utilities/misc.py
gracklepy/utilities/model_tests.py
gracklepy/utilities/physical_constants.py
gracklepy/utilities/primordial_equilibrium.py
gracklepy/utilities/testing.py
gracklepy/utilities/units.py
gracklepy.libs/libgcc_s-0cd532bd.so.1
gracklepy.libs/libgfortran-2c33b284.so.5.0.0
gracklepy.libs/libhdf5-ba62e4a4.so.310.5.1
gracklepy.libs/libquadmath-bb76a5fc.so.0.0.0
gracklepy-1.2.dist-info/METADATA
gracklepy-1.2.dist-info/WHEEL
gracklepy-1.2.dist-info/RECORD
gracklepy-1.2.dist-info/licenses/LICENSE
