Metadata-Version: 2.1
Name: gracklepy
Version: 1.2
Summary: A wrapper for the Grackle chemistry library
Keywords: simulation,chemistry,cooling,astronomy,astrophysics
License: BSD 3-Clause
Classifier: Development Status :: 5 - Production/Stable
Classifier: Environment :: Console
Classifier: Intended Audience :: Science/Research
Classifier: Topic :: Scientific/Engineering :: Astronomy
Classifier: License :: OSI Approved :: BSD License
Classifier: Operating System :: MacOS :: MacOS X
Classifier: Operating System :: POSIX :: Linux
Classifier: Operating System :: Unix
Classifier: Natural Language :: English
Classifier: Programming Language :: Python :: 3.10
Classifier: Programming Language :: Python :: 3.11
Classifier: Programming Language :: Python :: 3.12
Classifier: Programming Language :: Python :: 3.13
Project-URL: Homepage, https://github.com/grackle-project/grackle
Project-URL: Documentation, https://grackle.readthedocs.io/
Project-URL: Source, https://github.com/grackle-project/grackle
Project-URL: Tracker, https://github.com/grackle-project/grackle/issues
Requires-Python: >=3.10
Requires-Dist: h5py
Requires-Dist: numpy
Requires-Dist: matplotlib
Requires-Dist: yt>=4.0.2
Provides-Extra: dev
Requires-Dist: flake8; extra == "dev"
Requires-Dist: packaging; extra == "dev"
Requires-Dist: pytest; extra == "dev"
Requires-Dist: sphinx; extra == "dev"
Requires-Dist: sphinx-tabs; extra == "dev"
Requires-Dist: furo; extra == "dev"
